differentiable_randaugment/__init__.py
differentiable_randaugment/base.py
differentiable_randaugment/enhance.py
differentiable_randaugment/geometric.py
differentiable_randaugment/randaugment.py
differentiable_randaugment-0.1.2.dist-info/LICENSE
differentiable_randaugment-0.1.2.dist-info/METADATA
differentiable_randaugment-0.1.2.dist-info/WHEEL
differentiable_randaugment-0.1.2.dist-info/top_level.txt
differentiable_randaugment-0.1.2.dist-info/RECORD
