Metadata-Version: 2.1
Name: differentiable-randaugment
Version: 0.1.2
Summary: Optimize RandAugment with differentiable operations
Home-page: https://github.com/affjljoo3581/Differentiable-RandAugment
Author: affjljoo3581
Author-email: affjljoo3581@gmail.com
License: Apache-2.0
Keywords: dataset,deep-learning,machine-learning,augmentation,image,computer-vision,overfitting
Platform: UNKNOWN
Classifier: Intended Audience :: Science/Research
Classifier: Intended Audience :: Developers
Classifier: Intended Audience :: Information Technology
Classifier: Operating System :: OS Independent
Classifier: Programming Language :: Python :: 3
Classifier: Programming Language :: Python :: 3.7
Classifier: Programming Language :: Python :: 3.8
Classifier: Topic :: Scientific/Engineering :: Artificial Intelligence
Classifier: Topic :: Scientific/Engineering :: Image Recognition
Classifier: Topic :: Software Development :: Libraries :: Python Modules
Requires-Python: >=3.7
Requires-Dist: opencv-python
Requires-Dist: torch (>=1.7)
Requires-Dist: albumentations
Requires-Dist: numpy
Provides-Extra: tests
Requires-Dist: pytest ; extra == 'tests'
